fundsight/__init__.py
fundsight/indicators.py
fundsight-0.0.2.dist-info/LICENSE
fundsight-0.0.2.dist-info/METADATA
fundsight-0.0.2.dist-info/WHEEL
fundsight-0.0.2.dist-info/top_level.txt
fundsight-0.0.2.dist-info/RECORD
