Metadata-Version: 2.1
Name: fundsight
Version: 0.0.2
Summary: Asset management fund performance and reporting modules
Home-page: https://github.com/ahgperrin/fundsight
Author: Antoine Perrin
Author-email: antoineperrin.pro1@gmail.com
License: UNKNOWN
Platform: UNKNOWN
Classifier: Programming Language :: Python :: 3.9
Classifier: License :: OSI Approved :: MIT License
Classifier: Operating System :: OS Independent
Requires-Dist: workalendar
Requires-Dist: pandas
Requires-Dist: numpy
Requires-Dist: datetime
